powergama/GridData.py
powergama/LpProblemPyomo.py
powergama/Results.py
powergama/__init__.py
powergama/constants.py
powergama/costbenefit.py
powergama/database.py
powergama/fault_scenarios/LpFaultProblem.py
powergama/fault_scenarios/__init__.py
powergama/fault_scenarios/failure_situation.py
powergama/fault_scenarios/full_profiles.py
powergama/fault_scenarios/generate_failure_situations.py
powergama/fault_scenarios/loadshedding_stats.py
powergama/fault_scenarios/specify_storage.py
powergama/filters.py
powergama/plots.py
powergama/scenarios.py
powergama-1.5.1.dist-info/METADATA
powergama-1.5.1.dist-info/WHEEL
powergama-1.5.1.dist-info/licenses/LICENCE.txt
powergama-1.5.1.dist-info/RECORD
