Metadata-Version: 2.4
Name: powergama
Version: 1.5.1
Summary: PowerGAMA - Power Grid And Market Analysis tool)
License: MIT
License-File: LICENCE.txt
Author: Harald G Svendsen
Author-email: harald.svendsen@sintef.no
Requires-Python: >=3.11
Classifier: Development Status :: 4 - Beta
Classifier: Topic :: Scientific/Engineering
Classifier: Operating System :: Microsoft :: Windows
Classifier: Operating System :: MacOS
Classifier: Operating System :: POSIX :: Linux
Classifier: Programming Language :: Python :: 3
Classifier: Natural Language :: English
Classifier: License :: OSI Approved :: MIT License
Requires-Dist: branca (>=0.8)
Requires-Dist: cloudpickle (>=3.1)
Requires-Dist: folium (>=0.20)
Requires-Dist: geopandas (>=1.1)
Requires-Dist: highspy (>=1.12)
Requires-Dist: matplotlib (>=3.10)
Requires-Dist: networkx (>=3.5)
Requires-Dist: numpy (>=2.3)
Requires-Dist: pandas (>=2.3)
Requires-Dist: pyomo (>=6.9)
Requires-Dist: scipy (>=1.16)
Requires-Dist: tqdm (>=4.67)
Project-URL: Homepage, https://github.com/powergama/powergama
